MANIFEST.in
README.md
requirements.txt
setup.py
pylint_tta/__init__.py
pylint_tta.egg-info/PKG-INFO
pylint_tta.egg-info/SOURCES.txt
pylint_tta.egg-info/dependency_links.txt
pylint_tta.egg-info/requires.txt
pylint_tta.egg-info/top_level.txt
pylint_tta.egg-info/zip-safe