Metadata-Version: 2.1
Name: pylint-tta
Version: 0.0.4a0
Summary: Linter for PyTorch Tensor operations
Home-page: https://github.com/Popgun-Labs/pylint-tta
Author: Kendrick Tan
Author-email: kendrick@wearepopgun.com
License: UNKNOWN
Platform: UNKNOWN
